VascoCal/Calculadora.py
VascoCal/__init__.py
vascocal-0.2.0.dist-info/METADATA
vascocal-0.2.0.dist-info/WHEEL
vascocal-0.2.0.dist-info/top_level.txt
vascocal-0.2.0.dist-info/RECORD
